emailtrail/__init__.py
emailtrail/models.py
emailtrail/module.py
emailtrail/utils.py
emailtrail-0.4.0.dist-info/LICENSE.txt
emailtrail-0.4.0.dist-info/WHEEL
emailtrail-0.4.0.dist-info/METADATA
emailtrail-0.4.0.dist-info/RECORD
